{
  "company": "Chevron",
  "ticker": "CVX",
  "slug": "chevron",
  "sector": "Energy",
  "currency": "USD",
  "country": "US",
  "index": "S&P 500",
  "description": "Data sourced via yfinance / Yahoo Finance. Approximation.",
  "observations": [
    {
      "periodKey": "2025_q4",
      "periodLabel": "Q4 2025",
      "rg8": 1.01,
      "rg10": 0.98,
      "rg12": 0.98,
      "trend": "+",
      "marketCap": 397.8,
      "bookEquity": 181.9,
      "netIncome": 11.1,
      "fundamentalBaseApprox": 407.26,
      "dataType": "quarterly",
      "note": "Computed via yfinance. Older quarters estimated from annual NI / 4. Historical market cap not adjusted. Approximation."
    },
    {
      "periodKey": "2025_q3",
      "periodLabel": "Q3 2025",
      "rg8": 0.94,
      "rg10": 0.95,
      "rg12": 0.96,
      "trend": "=",
      "marketCap": 397.8,
      "bookEquity": 181.9,
      "netIncome": 14.2,
      "fundamentalBaseApprox": 417.55,
      "dataType": "quarterly",
      "note": "Computed via yfinance. Older quarters estimated from annual NI / 4. Historical market cap not adjusted. Approximation."
    },
    {
      "periodKey": "2025_q2",
      "periodLabel": "Q2 2025",
      "rg8": 0.92,
      "rg10": 0.94,
      "rg12": 0.95,
      "trend": "+",
      "marketCap": 397.8,
      "bookEquity": 181.9,
      "netIncome": 10.0,
      "fundamentalBaseApprox": 424.76,
      "dataType": "quarterly",
      "note": "Computed via yfinance. Older quarters estimated from annual NI / 4. Historical market cap not adjusted. Approximation."
    },
    {
      "periodKey": "2025_q1",
      "periodLabel": "Q1 2025",
      "rg8": 0.89,
      "rg10": 0.91,
      "rg12": 0.94,
      "trend": "++",
      "marketCap": 397.8,
      "bookEquity": 181.9,
      "netIncome": 14.0,
      "fundamentalBaseApprox": 436.17,
      "dataType": "quarterly",
      "note": "Computed via yfinance. Older quarters estimated from annual NI / 4. Historical market cap not adjusted. Approximation."
    },
    {
      "periodKey": "2024_q4",
      "periodLabel": "Q4 2024",
      "rg8": 0.74,
      "rg10": 0.68,
      "rg12": 0.65,
      "trend": null,
      "marketCap": 279.7,
      "bookEquity": 181.9,
      "netIncome": 17.7,
      "fundamentalBaseApprox": 408.93,
      "dataType": "annual",
      "note": "Annual historical observation. Market cap approximated from historical close price × current shares outstanding. Earnings smoothed from available annual data. Approximation."
    },
    {
      "periodKey": "2023_q4",
      "periodLabel": "Q4 2023",
      "rg8": 0.57,
      "rg10": null,
      "rg12": null,
      "trend": null,
      "marketCap": 265.0,
      "bookEquity": 181.9,
      "netIncome": 21.4,
      "fundamentalBaseApprox": 181.88,
      "dataType": "annual",
      "note": "Annual historical observation. Market cap approximated from historical close price × current shares outstanding. Earnings smoothed from available annual data. Approximation."
    }
  ]
}